setup.py
amphora/__init__.py
amphora/base.py
amphora/client.py
amphora/consumer.py
amphora/exception.py
amphora/publisher.py
amphora/serializer.py
amphora/server.py
amphora.egg-info/PKG-INFO
amphora.egg-info/SOURCES.txt
amphora.egg-info/dependency_links.txt
amphora.egg-info/requires.txt
amphora.egg-info/top_level.txt