Metadata-Version: 1.1
Name: amphora
Version: 0.1.1
Summary: AMQP RPC for services based on gevent
Home-page: http://bitbucket.org/werehuman/amphora/
Author: Vladimir Lagunov
Author-email: lagunov.vladimir@gmail.com
License: BSD v3
Keywords: AMQP,RPC,gevent
Platform: UNKNOWN
Classifier: License :: OSI Approved :: MIT License
Classifier: Programming Language :: Python :: 2.6
Classifier: Programming Language :: Python :: 2.7
Classifier: Operating System :: MacOS :: MacOS X
Classifier: Operating System :: POSIX
Classifier: Topic :: Internet
Classifier: Topic :: Software Development :: Libraries :: Python Modules
Classifier: Intended Audience :: Developers
Classifier: Development Status :: 4 - Beta
